shippingtracker/__init__.py
shippingtracker/main.py
shippingtracker-0.1.2.dist-info/METADATA
shippingtracker-0.1.2.dist-info/WHEEL
shippingtracker-0.1.2.dist-info/entry_points.txt
shippingtracker-0.1.2.dist-info/licenses/LICENSE
shippingtracker-0.1.2.dist-info/RECORD
