Metadata-Version: 2.4
Name: shippingtracker
Version: 0.1.2
Summary: Korean shipping tracker MCP server using SweetTracker API
Project-URL: Homepage, https://github.com/gws8820/shippingtracker
Project-URL: Repository, https://github.com/gws8820/shippingtracker
License-File: LICENSE
Requires-Python: >=3.13
Requires-Dist: mcp[cli]>=1.13.0
Requires-Dist: requests>=2.32.4
